geoh5py/__init__.py
geoh5py/data/__init__.py
geoh5py/data/blob_data.py
geoh5py/data/boolean_data.py
geoh5py/data/color_map.py
geoh5py/data/colour.py
geoh5py/data/data.py
geoh5py/data/data_association_enum.py
geoh5py/data/data_type.py
geoh5py/data/data_unit.py
geoh5py/data/datetime_data.py
geoh5py/data/filename_data.py
geoh5py/data/float_data.py
geoh5py/data/geometric_data.py
geoh5py/data/integer_data.py
geoh5py/data/numeric_data.py
geoh5py/data/primitive_type_enum.py
geoh5py/data/reference_value_map.py
geoh5py/data/referenced_data.py
geoh5py/data/text_data.py
geoh5py/data/unknown_data.py
geoh5py/data/visual_parameters.py
geoh5py/groups/__init__.py
geoh5py/groups/base.py
geoh5py/groups/container.py
geoh5py/groups/custom.py
geoh5py/groups/drillhole.py
geoh5py/groups/giftools.py
geoh5py/groups/group_type.py
geoh5py/groups/integrator.py
geoh5py/groups/interpretation_section.py
geoh5py/groups/maps.py
geoh5py/groups/notype.py
geoh5py/groups/property_group.py
geoh5py/groups/property_group_table.py
geoh5py/groups/property_group_type.py
geoh5py/groups/root.py
geoh5py/groups/simpeg.py
geoh5py/groups/survey.py
geoh5py/groups/uijson.py
geoh5py/io/__init__.py
geoh5py/io/h5_reader.py
geoh5py/io/h5_writer.py
geoh5py/io/utils.py
geoh5py/objects/__init__.py
geoh5py/objects/block_model.py
geoh5py/objects/cell_object.py
geoh5py/objects/curve.py
geoh5py/objects/drape_model.py
geoh5py/objects/drillhole.py
geoh5py/objects/geo_image.py
geoh5py/objects/grid2d.py
geoh5py/objects/grid_object.py
geoh5py/objects/integrator.py
geoh5py/objects/label.py
geoh5py/objects/notype_object.py
geoh5py/objects/object_base.py
geoh5py/objects/object_type.py
geoh5py/objects/octree.py
geoh5py/objects/points.py
geoh5py/objects/slicer.py
geoh5py/objects/surface.py
geoh5py/objects/surveys/__init__.py
geoh5py/objects/surveys/base.py
geoh5py/objects/surveys/direct_current.py
geoh5py/objects/surveys/electromagnetics/__init__.py
geoh5py/objects/surveys/electromagnetics/airborne_fem.py
geoh5py-0.11.0.dist-info/COPYING
geoh5py-0.11.0.dist-info/COPYING.LESSER
geoh5py-0.11.0.dist-info/METADATA
geoh5py-0.11.0.dist-info/WHEEL
geoh5py-0.11.0.dist-info/RECORD
