Metadata-Version: 2.3
Name: geoh5py
Version: 0.11.0
Summary: Python API for geoh5, an open file format for geoscientific data
License: LGPL-3.0-or-later
Keywords: geology,geophysics,data,interoperability
Author: Mira Geoscience
Author-email: support@mirageoscience.com
Maintainer: Benjamin Kary
Maintainer-email: benjamink@mirageoscience.com
Requires-Python: >=3.10,<4.0
Classifier: Development Status :: 4 - Beta
Classifier: Intended Audience :: Developers
Classifier: Intended Audience :: Science/Research
Classifier: License :: OSI Approved :: GNU Lesser General Public License v3 or later (LGPLv3+)
Classifier: Natural Language :: English
Classifier: Programming Language :: Python :: 3
Classifier: Programming Language :: Python :: 3.10
Classifier: Programming Language :: Python :: 3.11
Classifier: Programming Language :: Python :: 3.12
Classifier: Programming Language :: Python :: 3.13
Classifier: Topic :: Database
Classifier: Topic :: Scientific/Engineering
Classifier: Topic :: Scientific/Engineering :: Mathematics
Classifier: Topic :: Scientific/Engineering :: Physics
Classifier: Topic :: Software Development :: Libraries :: Python Modules
Requires-Dist: Pillow (>=10.3.0,<10.4.0)
Requires-Dist: h5py (>=3.2.1,<4.0.0)
Requires-Dist: numpy (>=1.26.0,<1.27.0)
Requires-Dist: pydantic (>=2.5.2,<3.0.0)
Project-URL: Documentation, https://mirageoscience-geoh5py.readthedocs-hosted.com/
Project-URL: Homepage, https://www.mirageoscience.com/mining-industry-software/python-integration/
Project-URL: Repository, https://github.com/MiraGeoscience/geoh5py
